<dc xmlns:dnb="http://d-nb.de/standards/dnbterms" xmlns="http://www.openarchives.org/OAI/2.0/oai_dc/" xmlns:dc="http://purl.org/dc/elements/1.1/" xmlns:xsi="http://www.w3.org/2001/XMLSchema-instance">
  <dc:title>The workers' call</dc:title>
  <dc:publisher>Chicago, Ill.</dc:publisher>
  <dc:date>Nachgewiesen 1899,11.März - 1902,1.März</dc:date>
  <dc:identifier xsi:type="dnb:IDN">010592458</dc:identifier>
  <dc:identifier xsi:type="dnb:ZDBID">87286-6</dc:identifier>
  <dc:relation>http://d-nb.info/01059244X</dc:relation>
</dc>