<dc xmlns:dnb="http://d-nb.de/standards/dnbterms" xmlns="http://www.openarchives.org/OAI/2.0/oai_dc/" xmlns:dc="http://purl.org/dc/elements/1.1/" xmlns:xsi="http://www.w3.org/2001/XMLSchema-instance">
  <dc:title>The review</dc:title>
  <dc:publisher>Nashville, Tenn.</dc:publisher>
  <dc:date>4.1809,10.Nov. - 6.1811,3.Mai[?]</dc:date>
  <dc:language>eng</dc:language>
  <dc:identifier xsi:type="dnb:IDN">016410017</dc:identifier>
  <dc:identifier xsi:type="dnb:ZDBID">1111267-0</dc:identifier>
</dc>