<dc xmlns:dnb="http://d-nb.de/standards/dnbterms" xmlns="http://www.openarchives.org/OAI/2.0/oai_dc/" xmlns:dc="http://purl.org/dc/elements/1.1/" xmlns:xsi="http://www.w3.org/2001/XMLSchema-instance">
  <dc:title>Dedham gazette</dc:title>
  <dc:publisher>Dedham, Mass. : Hall</dc:publisher>
  <dc:date>1.1813/14,1(20.Aug.) - 6.1818/19,46(25.Juni)[?]</dc:date>
  <dc:language>eng</dc:language>
  <dc:identifier xsi:type="dnb:IDN">017273293</dc:identifier>
  <dc:identifier xsi:type="dnb:ZDBID">1200344-x</dc:identifier>
</dc>