<dc xmlns:dnb="http://d-nb.de/standards/dnbterms" xmlns="http://www.openarchives.org/OAI/2.0/oai_dc/" xmlns:dc="http://purl.org/dc/elements/1.1/" xmlns:xsi="http://www.w3.org/2001/XMLSchema-instance">
  <dc:title>Easton gazette, and Eastern Shore intelligencer</dc:title>
  <dc:publisher>Easton, Md.</dc:publisher>
  <dc:date>Nachgewiesen 1821,6.Jan. - 1822,3.Febr.</dc:date>
  <dc:language>eng</dc:language>
  <dc:identifier xsi:type="dnb:IDN">1014291313</dc:identifier>
  <dc:identifier xsi:type="dnb:ZDBID">2623352-6</dc:identifier>
  <dc:relation>http://d-nb.info/1014292042</dc:relation>
</dc>